[
{ 
"r030":31,"txt":"Азербайджанський манат","rate":0.000536,"cc":"AZM","exchangedate":"06.07.1998"
 }
,{ 
"r030":36,"txt":"Австралійський долар","rate":1.2758,"cc":"AUD","exchangedate":"06.07.1998"
 }
,{ 
"r030":40,"txt":"Австрійський шилінг","rate":0.162,"cc":"ATS","exchangedate":"06.07.1998"
 }
,{ 
"r030":56,"txt":"Бельгійський франк","rate":0.05525,"cc":"BEF","exchangedate":"06.07.1998"
 }
,{ 
"r030":112,"txt":"Бiлоруський рубль","rate":0.00003765,"cc":"BYB","exchangedate":"06.07.1998"
 }
,{ 
"r030":124,"txt":"Канадський долар","rate":1.412,"cc":"CAD","exchangedate":"06.07.1998"
 }
,{ 
"r030":203,"txt":"Чеська крона","rate":0.0617,"cc":"CZK","exchangedate":"06.07.1998"
 }
,{ 
"r030":208,"txt":"Данська крона","rate":0.2991,"cc":"DKK","exchangedate":"06.07.1998"
 }
,{ 
"r030":233,"txt":"Крони Естонії","rate":0.1424,"cc":"EEK","exchangedate":"06.07.1998"
 }
,{ 
"r030":246,"txt":"Фінські маpки","rate":0.3749,"cc":"FIM","exchangedate":"06.07.1998"
 }
,{ 
"r030":250,"txt":"Фpанцузський фpанк","rate":0.3399,"cc":"FRF","exchangedate":"06.07.1998"
 }
,{ 
"r030":280,"txt":"Hімецькі маpки","rate":1.1394,"cc":"DEM","exchangedate":"06.07.1998"
 }
,{ 
"r030":348,"txt":"Форинт","rate":0.00945,"cc":"HUF","exchangedate":"06.07.1998"
 }
,{ 
"r030":352,"txt":"Ісландські крони","rate":0.0288,"cc":"ISK","exchangedate":"06.07.1998"
 }
,{ 
"r030":380,"txt":"Італійські ліpи","rate":0.001156,"cc":"ITL","exchangedate":"06.07.1998"
 }
,{ 
"r030":392,"txt":"Єна","rate":0.01485,"cc":"JPY","exchangedate":"06.07.1998"
 }
,{ 
"r030":398,"txt":"Теньге","rate":0.0268,"cc":"KZT","exchangedate":"06.07.1998"
 }
,{ 
"r030":428,"txt":"Лати Латвії","rate":3.4526,"cc":"LVL","exchangedate":"06.07.1998"
 }
,{ 
"r030":440,"txt":"Литовські лити","rate":0.517,"cc":"LTL","exchangedate":"06.07.1998"
 }
,{ 
"r030":498,"txt":"Молдовський лей","rate":0.4358,"cc":"MDL","exchangedate":"06.07.1998"
 }
,{ 
"r030":528,"txt":"Голандські гульдени","rate":1.0108,"cc":"NLG","exchangedate":"06.07.1998"
 }
,{ 
"r030":578,"txt":"Норвезька крона","rate":0.267,"cc":"NOK","exchangedate":"06.07.1998"
 }
,{ 
"r030":702,"txt":"Сінгапурський долар","rate":1.2299,"cc":"SGD","exchangedate":"06.07.1998"
 }
,{ 
"r030":703,"txt":"Словацькі крони","rate":0.0588,"cc":"SKK","exchangedate":"06.07.1998"
 }
,{ 
"r030":724,"txt":"Іспанскі пессети","rate":0.01343,"cc":"ESP","exchangedate":"06.07.1998"
 }
,{ 
"r030":752,"txt":"Шведська крона","rate":0.2569,"cc":"SEK","exchangedate":"06.07.1998"
 }
,{ 
"r030":756,"txt":"Швейцарський франк","rate":1.3536,"cc":"CHF","exchangedate":"06.07.1998"
 }
,{ 
"r030":792,"txt":"Турецькі ліри","rate":0.000008,"cc":"TRL","exchangedate":"06.07.1998"
 }
,{ 
"r030":795,"txt":"Манати Туркменії","rate":0.000398,"cc":"TMM","exchangedate":"06.07.1998"
 }
,{ 
"r030":826,"txt":"Фунт стерлінгів","rate":3.4109,"cc":"GBP","exchangedate":"06.07.1998"
 }
,{ 
"r030":840,"txt":"Долар США","rate":2.0681,"cc":"USD","exchangedate":"06.07.1998"
 }
,{ 
"r030":860,"txt":"Узбецький сум","rate":0.0221,"cc":"UZS","exchangedate":"06.07.1998"
 }
,{ 
"r030":954,"txt":"ЕКЮ","rate":2.2553,"cc":"XEU","exchangedate":"06.07.1998"
 }
,{ 
"r030":960,"txt":"СПЗ(спец.права запозичення)","rate":2.7548,"cc":"XDR","exchangedate":"06.07.1998"
 }
,{ 
"r030":985,"txt":"Злотий","rate":0.5887,"cc":"PLN","exchangedate":"06.07.1998"
 }
,{ 
"r030":300,"txt":"Грецькі драхми","rate":0.0068,"cc":"GRD","exchangedate":"06.07.1998"
 }
,{ 
"r030":372,"txt":"Ірландські фунти","rate":2.8697,"cc":"IEP","exchangedate":"06.07.1998"
 }
,{ 
"r030":620,"txt":"Португальські ескудо","rate":0.00111,"cc":"PTE","exchangedate":"06.07.1998"
 }
,{ 
"r030":810,"txt":"Російські рублі","rate":0.333,"cc":"RUR","exchangedate":"06.07.1998"
 }
]
