[
{ 
"r030":31,"txt":"Азербайджанський манат","rate":0.00103884,"cc":"AZM","exchangedate":"30.10.1999"
 }
,{ 
"r030":36,"txt":"Австралійський долар","rate":2.881172,"cc":"AUD","exchangedate":"30.10.1999"
 }
,{ 
"r030":40,"txt":"Австрійський шилінг","rate":0.342571,"cc":"ATS","exchangedate":"30.10.1999"
 }
,{ 
"r030":56,"txt":"Бельгійський франк","rate":0.1168542,"cc":"BEF","exchangedate":"30.10.1999"
 }
,{ 
"r030":112,"txt":"Бiлоруський рубль","rate":0.00001126,"cc":"BYB","exchangedate":"30.10.1999"
 }
,{ 
"r030":124,"txt":"Канадський долар","rate":3.057192,"cc":"CAD","exchangedate":"30.10.1999"
 }
,{ 
"r030":203,"txt":"Чеська крона","rate":0.131251,"cc":"CZK","exchangedate":"30.10.1999"
 }
,{ 
"r030":208,"txt":"Данська крона","rate":0.634124,"cc":"DKK","exchangedate":"30.10.1999"
 }
,{ 
"r030":233,"txt":"Крони Естонії","rate":0.301272,"cc":"EEK","exchangedate":"30.10.1999"
 }
,{ 
"r030":246,"txt":"Фінські маpки","rate":0.792819,"cc":"FIM","exchangedate":"30.10.1999"
 }
,{ 
"r030":250,"txt":"Фpанцузський фpанк","rate":0.718627,"cc":"FRF","exchangedate":"30.10.1999"
 }
,{ 
"r030":280,"txt":"Hімецькі маpки","rate":2.410171,"cc":"DEM","exchangedate":"30.10.1999"
 }
,{ 
"r030":348,"txt":"Форинт","rate":0.0187431,"cc":"HUF","exchangedate":"30.10.1999"
 }
,{ 
"r030":352,"txt":"Ісландські крони","rate":0.063602,"cc":"ISK","exchangedate":"30.10.1999"
 }
,{ 
"r030":380,"txt":"Італійські ліpи","rate":0.00243452,"cc":"ITL","exchangedate":"30.10.1999"
 }
,{ 
"r030":392,"txt":"Єна","rate":0.0430138,"cc":"JPY","exchangedate":"30.10.1999"
 }
,{ 
"r030":398,"txt":"Теньге","rate":0.032028,"cc":"KZT","exchangedate":"30.10.1999"
 }
,{ 
"r030":428,"txt":"Лати Латвії","rate":7.829167,"cc":"LVL","exchangedate":"30.10.1999"
 }
,{ 
"r030":440,"txt":"Литовські лити","rate":1.1274,"cc":"LTL","exchangedate":"30.10.1999"
 }
,{ 
"r030":498,"txt":"Молдовський лей","rate":0.403158,"cc":"MDL","exchangedate":"30.10.1999"
 }
,{ 
"r030":528,"txt":"Голандські гульдени","rate":2.139068,"cc":"NLG","exchangedate":"30.10.1999"
 }
,{ 
"r030":578,"txt":"Норвезька крона","rate":0.571657,"cc":"NOK","exchangedate":"30.10.1999"
 }
,{ 
"r030":702,"txt":"Сінгапурський долар","rate":2.709282,"cc":"SGD","exchangedate":"30.10.1999"
 }
,{ 
"r030":703,"txt":"Словацькі крони","rate":0.110209,"cc":"SKK","exchangedate":"30.10.1999"
 }
,{ 
"r030":724,"txt":"Іспанскі пессети","rate":0.028331,"cc":"ESP","exchangedate":"30.10.1999"
 }
,{ 
"r030":752,"txt":"Шведська крона","rate":0.544329,"cc":"SEK","exchangedate":"30.10.1999"
 }
,{ 
"r030":756,"txt":"Швейцарський франк","rate":2.940664,"cc":"CHF","exchangedate":"30.10.1999"
 }
,{ 
"r030":792,"txt":"Турецькі ліри","rate":0.00000948,"cc":"TRL","exchangedate":"30.10.1999"
 }
,{ 
"r030":795,"txt":"Манати Туркменії","rate":0.00086723,"cc":"TMM","exchangedate":"30.10.1999"
 }
,{ 
"r030":826,"txt":"Фунт стерлінгів","rate":7.37351,"cc":"GBP","exchangedate":"30.10.1999"
 }
,{ 
"r030":840,"txt":"Долар США","rate":4.5096,"cc":"USD","exchangedate":"30.10.1999"
 }
,{ 
"r030":860,"txt":"Узбецький сум","rate":0.03291,"cc":"UZS","exchangedate":"30.10.1999"
 }
,{ 
"r030":960,"txt":"СПЗ(спец.права запозичення)","rate":6.201746,"cc":"XDR","exchangedate":"30.10.1999"
 }
,{ 
"r030":978,"txt":"Євро","rate":4.713885,"cc":"EUR","exchangedate":"30.10.1999"
 }
,{ 
"r030":985,"txt":"Злотий","rate":1.094165,"cc":"PLN","exchangedate":"30.10.1999"
 }
,{ 
"r030":300,"txt":"Грецькі драхми","rate":0.0142819,"cc":"GRD","exchangedate":"30.10.1999"
 }
,{ 
"r030":372,"txt":"Ірландські фунти","rate":5.985399,"cc":"IEP","exchangedate":"30.10.1999"
 }
,{ 
"r030":620,"txt":"Португальські ескудо","rate":0.0023513,"cc":"PTE","exchangedate":"30.10.1999"
 }
,{ 
"r030":810,"txt":"Російські рублі","rate":0.17311,"cc":"RUR","exchangedate":"30.10.1999"
 }
]
