[
{ 
"r030":31,"txt":"Азербайджанський манат","rate":0.00087804,"cc":"AZM","exchangedate":"08.02.1999"
 }
,{ 
"r030":36,"txt":"Австралійський долар","rate":2.237636,"cc":"AUD","exchangedate":"08.02.1999"
 }
,{ 
"r030":40,"txt":"Австрійський шилінг","rate":0.281227,"cc":"ATS","exchangedate":"08.02.1999"
 }
,{ 
"r030":56,"txt":"Бельгійський франк","rate":0.0959291,"cc":"BEF","exchangedate":"08.02.1999"
 }
,{ 
"r030":124,"txt":"Канадський долар","rate":2.308242,"cc":"CAD","exchangedate":"08.02.1999"
 }
,{ 
"r030":203,"txt":"Чеська крона","rate":0.105644,"cc":"CZK","exchangedate":"08.02.1999"
 }
,{ 
"r030":208,"txt":"Данська крона","rate":0.520424,"cc":"DKK","exchangedate":"08.02.1999"
 }
,{ 
"r030":233,"txt":"Крони Естонії","rate":0.247323,"cc":"EEK","exchangedate":"08.02.1999"
 }
,{ 
"r030":246,"txt":"Фінські маpки","rate":0.650848,"cc":"FIM","exchangedate":"08.02.1999"
 }
,{ 
"r030":250,"txt":"Фpанцузський фpанк","rate":0.589942,"cc":"FRF","exchangedate":"08.02.1999"
 }
,{ 
"r030":280,"txt":"Hімецькі маpки","rate":1.978581,"cc":"DEM","exchangedate":"08.02.1999"
 }
,{ 
"r030":348,"txt":"Форинт","rate":0.0156241,"cc":"HUF","exchangedate":"08.02.1999"
 }
,{ 
"r030":352,"txt":"Ісландські крони","rate":0.048915,"cc":"ISK","exchangedate":"08.02.1999"
 }
,{ 
"r030":380,"txt":"Італійські ліpи","rate":0.00199857,"cc":"ITL","exchangedate":"08.02.1999"
 }
,{ 
"r030":392,"txt":"Єна","rate":0.0302444,"cc":"JPY","exchangedate":"08.02.1999"
 }
,{ 
"r030":398,"txt":"Теньге","rate":0.040318,"cc":"KZT","exchangedate":"08.02.1999"
 }
,{ 
"r030":428,"txt":"Лати Латвії","rate":5.970383,"cc":"LVL","exchangedate":"08.02.1999"
 }
,{ 
"r030":440,"txt":"Литовські лити","rate":0.85675,"cc":"LTL","exchangedate":"08.02.1999"
 }
,{ 
"r030":498,"txt":"Молдовський лей","rate":0.391662,"cc":"MDL","exchangedate":"08.02.1999"
 }
,{ 
"r030":528,"txt":"Голандські гульдени","rate":1.756024,"cc":"NLG","exchangedate":"08.02.1999"
 }
,{ 
"r030":578,"txt":"Норвезька крона","rate":0.446211,"cc":"NOK","exchangedate":"08.02.1999"
 }
,{ 
"r030":702,"txt":"Сінгапурський долар","rate":2.025055,"cc":"SGD","exchangedate":"08.02.1999"
 }
,{ 
"r030":703,"txt":"Словацькі крони","rate":0.092483,"cc":"SKK","exchangedate":"08.02.1999"
 }
,{ 
"r030":724,"txt":"Іспанскі пессети","rate":0.0232578,"cc":"ESP","exchangedate":"08.02.1999"
 }
,{ 
"r030":752,"txt":"Шведська крона","rate":0.436178,"cc":"SEK","exchangedate":"08.02.1999"
 }
,{ 
"r030":756,"txt":"Швейцарський франк","rate":2.416793,"cc":"CHF","exchangedate":"08.02.1999"
 }
,{ 
"r030":792,"txt":"Турецькі ліри","rate":0.00001027,"cc":"TRL","exchangedate":"08.02.1999"
 }
,{ 
"r030":795,"txt":"Манати Туркменії","rate":0.00065904,"cc":"TMM","exchangedate":"08.02.1999"
 }
,{ 
"r030":826,"txt":"Фунт стерлінгів","rate":5.620579,"cc":"GBP","exchangedate":"08.02.1999"
 }
,{ 
"r030":840,"txt":"Долар США","rate":3.427,"cc":"USD","exchangedate":"08.02.1999"
 }
,{ 
"r030":860,"txt":"Узбецький сум","rate":0.030724,"cc":"UZS","exchangedate":"08.02.1999"
 }
,{ 
"r030":960,"txt":"СПЗ(спец.права запозичення)","rate":4.776147,"cc":"XDR","exchangedate":"08.02.1999"
 }
,{ 
"r030":978,"txt":"Євро","rate":3.869768,"cc":"EUR","exchangedate":"08.02.1999"
 }
,{ 
"r030":985,"txt":"Злотий","rate":0.932568,"cc":"PLN","exchangedate":"08.02.1999"
 }
,{ 
"r030":300,"txt":"Грецькі драхми","rate":0.0120198,"cc":"GRD","exchangedate":"08.02.1999"
 }
,{ 
"r030":372,"txt":"Ірландські фунти","rate":4.913592,"cc":"IEP","exchangedate":"08.02.1999"
 }
,{ 
"r030":620,"txt":"Португальські ескудо","rate":0.0019302,"cc":"PTE","exchangedate":"08.02.1999"
 }
,{ 
"r030":810,"txt":"Російські рублі","rate":0.14823,"cc":"RUR","exchangedate":"08.02.1999"
 }
]
