[
{ 
"r030":31,"txt":"Азербайджанський манат","rate":0.00102443,"cc":"AZM","exchangedate":"01.09.1999"
 }
,{ 
"r030":36,"txt":"Австралійський долар","rate":2.794785,"cc":"AUD","exchangedate":"01.09.1999"
 }
,{ 
"r030":40,"txt":"Австрійський шилінг","rate":0.336423,"cc":"ATS","exchangedate":"01.09.1999"
 }
,{ 
"r030":56,"txt":"Бельгійський франк","rate":0.1147569,"cc":"BEF","exchangedate":"01.09.1999"
 }
,{ 
"r030":124,"txt":"Канадський долар","rate":2.938667,"cc":"CAD","exchangedate":"01.09.1999"
 }
,{ 
"r030":203,"txt":"Чеська крона","rate":0.124888,"cc":"CZK","exchangedate":"01.09.1999"
 }
,{ 
"r030":208,"txt":"Данська крона","rate":0.622684,"cc":"DKK","exchangedate":"01.09.1999"
 }
,{ 
"r030":233,"txt":"Крони Естонії","rate":0.295865,"cc":"EEK","exchangedate":"01.09.1999"
 }
,{ 
"r030":246,"txt":"Фінські маpки","rate":0.778589,"cc":"FIM","exchangedate":"01.09.1999"
 }
,{ 
"r030":250,"txt":"Фpанцузський фpанк","rate":0.70573,"cc":"FRF","exchangedate":"01.09.1999"
 }
,{ 
"r030":280,"txt":"Hімецькі маpки","rate":2.366914,"cc":"DEM","exchangedate":"01.09.1999"
 }
,{ 
"r030":348,"txt":"Форинт","rate":0.0180956,"cc":"HUF","exchangedate":"01.09.1999"
 }
,{ 
"r030":352,"txt":"Ісландські крони","rate":0.05979,"cc":"ISK","exchangedate":"01.09.1999"
 }
,{ 
"r030":380,"txt":"Італійські ліpи","rate":0.00239082,"cc":"ITL","exchangedate":"01.09.1999"
 }
,{ 
"r030":392,"txt":"Єна","rate":0.04007,"cc":"JPY","exchangedate":"01.09.1999"
 }
,{ 
"r030":398,"txt":"Теньге","rate":0.03317,"cc":"KZT","exchangedate":"01.09.1999"
 }
,{ 
"r030":428,"txt":"Лати Латвії","rate":7.471672,"cc":"LVL","exchangedate":"01.09.1999"
 }
,{ 
"r030":440,"txt":"Литовські лити","rate":1.0946,"cc":"LTL","exchangedate":"01.09.1999"
 }
,{ 
"r030":498,"txt":"Молдовський лей","rate":0.397415,"cc":"MDL","exchangedate":"01.09.1999"
 }
,{ 
"r030":528,"txt":"Голандські гульдени","rate":2.100677,"cc":"NLG","exchangedate":"01.09.1999"
 }
,{ 
"r030":578,"txt":"Норвезька крона","rate":0.559126,"cc":"NOK","exchangedate":"01.09.1999"
 }
,{ 
"r030":702,"txt":"Сінгапурський долар","rate":2.593839,"cc":"SGD","exchangedate":"01.09.1999"
 }
,{ 
"r030":703,"txt":"Словацькі крони","rate":0.103476,"cc":"SKK","exchangedate":"01.09.1999"
 }
,{ 
"r030":724,"txt":"Іспанскі пессети","rate":0.0278225,"cc":"ESP","exchangedate":"01.09.1999"
 }
,{ 
"r030":752,"txt":"Шведська крона","rate":0.532652,"cc":"SEK","exchangedate":"01.09.1999"
 }
,{ 
"r030":756,"txt":"Швейцарський франк","rate":2.893844,"cc":"CHF","exchangedate":"01.09.1999"
 }
,{ 
"r030":792,"txt":"Турецькі ліри","rate":0.00000978,"cc":"TRL","exchangedate":"01.09.1999"
 }
,{ 
"r030":795,"txt":"Манати Туркменії","rate":0.000842,"cc":"TMM","exchangedate":"01.09.1999"
 }
,{ 
"r030":826,"txt":"Фунт стерлінгів","rate":7.030041,"cc":"GBP","exchangedate":"01.09.1999"
 }
,{ 
"r030":840,"txt":"Долар США","rate":4.3784,"cc":"USD","exchangedate":"01.09.1999"
 }
,{ 
"r030":860,"txt":"Узбецький сум","rate":0.03275,"cc":"UZS","exchangedate":"01.09.1999"
 }
,{ 
"r030":960,"txt":"СПЗ(спец.права запозичення)","rate":6.027845,"cc":"XDR","exchangedate":"01.09.1999"
 }
,{ 
"r030":978,"txt":"Євро","rate":4.629282,"cc":"EUR","exchangedate":"01.09.1999"
 }
,{ 
"r030":985,"txt":"Злотий","rate":1.098858,"cc":"PLN","exchangedate":"01.09.1999"
 }
,{ 
"r030":51,"txt":"Вiрменський драм","rate":0.00813299,"cc":"AMD","exchangedate":"01.09.1999"
 }
,{ 
"r030":100,"txt":"Болгарські леви","rate":2.396084,"cc":"BGL","exchangedate":"01.09.1999"
 }
,{ 
"r030":112,"txt":"Бiлоруський рубль","rate":0.00001389,"cc":"BYB","exchangedate":"01.09.1999"
 }
,{ 
"r030":152,"txt":"Чілійські песо","rate":0.0085175,"cc":"CLP","exchangedate":"01.09.1999"
 }
,{ 
"r030":156,"txt":"Юань Женьмiньбi","rate":0.529272,"cc":"CNY","exchangedate":"01.09.1999"
 }
,{ 
"r030":191,"txt":"Куна","rate":0.613886,"cc":"HRK","exchangedate":"01.09.1999"
 }
,{ 
"r030":218,"txt":"Еквадорський сукре","rate":0.0003689,"cc":"ECS","exchangedate":"01.09.1999"
 }
,{ 
"r030":255,"txt":"Долари США по розр. з Індією","rate":3.5048,"cc":"___","exchangedate":"01.09.1999"
 }
,{ 
"r030":300,"txt":"Грецькі драхми","rate":0.014185,"cc":"GRD","exchangedate":"01.09.1999"
 }
,{ 
"r030":344,"txt":"Гонконгівський долар","rate":0.564264,"cc":"HKD","exchangedate":"01.09.1999"
 }
,{ 
"r030":356,"txt":"Індійська рупія","rate":0.1005624,"cc":"INR","exchangedate":"01.09.1999"
 }
,{ 
"r030":364,"txt":"Іранський ріал","rate":0.0014603,"cc":"IRR","exchangedate":"01.09.1999"
 }
,{ 
"r030":368,"txt":"Іракський динар","rate":14.100418,"cc":"IQD","exchangedate":"01.09.1999"
 }
,{ 
"r030":372,"txt":"Ірландські фунти","rate":5.877976,"cc":"IEP","exchangedate":"01.09.1999"
 }
,{ 
"r030":376,"txt":"Новий ізраїльський шекель","rate":1.033962,"cc":"ILS","exchangedate":"01.09.1999"
 }
,{ 
"r030":381,"txt":"Грузинські ларі","rate":2.392682,"cc":"GEL","exchangedate":"01.09.1999"
 }
,{ 
"r030":408,"txt":"Північнокрейський вон","rate":1.991364,"cc":"KPW","exchangedate":"01.09.1999"
 }
,{ 
"r030":410,"txt":"Вона","rate":0.0036508,"cc":"KRW","exchangedate":"01.09.1999"
 }
,{ 
"r030":414,"txt":"Кувейтські динари","rate":14.396977,"cc":"KWD","exchangedate":"01.09.1999"
 }
,{ 
"r030":417,"txt":"Сом","rate":0.103155,"cc":"KGS","exchangedate":"01.09.1999"
 }
,{ 
"r030":422,"txt":"Ліванський фунт","rate":0.0029139,"cc":"LBP","exchangedate":"01.09.1999"
 }
,{ 
"r030":434,"txt":"Лівійський динар","rate":9.735556,"cc":"LYD","exchangedate":"01.09.1999"
 }
,{ 
"r030":470,"txt":"Мальтійські ліри","rate":10.949763,"cc":"MTL","exchangedate":"01.09.1999"
 }
,{ 
"r030":484,"txt":"Мексіканський песо","rate":0.467556,"cc":"MXN","exchangedate":"01.09.1999"
 }
,{ 
"r030":496,"txt":"Монгольский тугрик","rate":0.00420748,"cc":"MNT","exchangedate":"01.09.1999"
 }
,{ 
"r030":554,"txt":"Новозеландський долар","rate":2.337281,"cc":"NZD","exchangedate":"01.09.1999"
 }
,{ 
"r030":586,"txt":"Пакистанська рупія","rate":0.084616,"cc":"PKR","exchangedate":"01.09.1999"
 }
,{ 
"r030":604,"txt":"Перуанский соль","rate":1.300386,"cc":"PEN","exchangedate":"01.09.1999"
 }
,{ 
"r030":620,"txt":"Португальські ескудо","rate":0.0023091,"cc":"PTE","exchangedate":"01.09.1999"
 }
,{ 
"r030":642,"txt":"новий румунські леї","rate":0.00027194,"cc":"ROL","exchangedate":"01.09.1999"
 }
,{ 
"r030":682,"txt":"Саудівський рiял","rate":1.168267,"cc":"SAR","exchangedate":"01.09.1999"
 }
,{ 
"r030":704,"txt":"Донг","rate":0.00031393,"cc":"VND","exchangedate":"01.09.1999"
 }
,{ 
"r030":705,"txt":"Словенські толари","rate":0.023753,"cc":"SIT","exchangedate":"01.09.1999"
 }
,{ 
"r030":760,"txt":"Сирійский фунт","rate":0.096925,"cc":"SYP","exchangedate":"01.09.1999"
 }
,{ 
"r030":762,"txt":"Таджикистанський сомоні","rate":0.0030508,"cc":"TJS","exchangedate":"01.09.1999"
 }
,{ 
"r030":810,"txt":"Російські рублі","rate":0.17648,"cc":"RUR","exchangedate":"01.09.1999"
 }
,{ 
"r030":818,"txt":"Єгипетський фунт","rate":1.284525,"cc":"EGP","exchangedate":"01.09.1999"
 }
,{ 
"r030":901,"txt":"Новий тайванський долар","rate":0.137228,"cc":"TWD","exchangedate":"01.09.1999"
 }
,{ 
"r030":952,"txt":"Франки CFA-BCEAO","rate":0.0071112,"cc":"XOF","exchangedate":"01.09.1999"
 }
,{ 
"r030":986,"txt":"Бразильський реал","rate":2.239203,"cc":"BRL","exchangedate":"01.09.1999"
 }
]
