[
{ 
"r030":31,"txt":"Азербайджанський манат","rate":0.00109203,"cc":"AZM","exchangedate":"19.07.2002"
 }
,{ 
"r030":36,"txt":"Австралійський долар","rate":2.940854,"cc":"AUD","exchangedate":"19.07.2002"
 }
,{ 
"r030":124,"txt":"Канадський долар","rate":3.457429,"cc":"CAD","exchangedate":"19.07.2002"
 }
,{ 
"r030":203,"txt":"Чеська крона","rate":0.180298,"cc":"CZK","exchangedate":"19.07.2002"
 }
,{ 
"r030":208,"txt":"Данська крона","rate":0.721147,"cc":"DKK","exchangedate":"19.07.2002"
 }
,{ 
"r030":233,"txt":"Крони Естонії","rate":0.342548,"cc":"EEK","exchangedate":"19.07.2002"
 }
,{ 
"r030":348,"txt":"Форинт","rate":0.0218898,"cc":"HUF","exchangedate":"19.07.2002"
 }
,{ 
"r030":352,"txt":"Ісландські крони","rate":0.063602,"cc":"ISK","exchangedate":"19.07.2002"
 }
,{ 
"r030":392,"txt":"Єна","rate":0.045537,"cc":"JPY","exchangedate":"19.07.2002"
 }
,{ 
"r030":398,"txt":"Теньге","rate":0.034681,"cc":"KZT","exchangedate":"19.07.2002"
 }
,{ 
"r030":428,"txt":"Лати Латвії","rate":8.955966,"cc":"LVL","exchangedate":"19.07.2002"
 }
,{ 
"r030":440,"txt":"Литовські лити","rate":1.553043,"cc":"LTL","exchangedate":"19.07.2002"
 }
,{ 
"r030":498,"txt":"Молдовський лей","rate":0.389461,"cc":"MDL","exchangedate":"19.07.2002"
 }
,{ 
"r030":578,"txt":"Норвезька крона","rate":0.726149,"cc":"NOK","exchangedate":"19.07.2002"
 }
,{ 
"r030":702,"txt":"Сінгапурський долар","rate":3.0571,"cc":"SGD","exchangedate":"19.07.2002"
 }
,{ 
"r030":703,"txt":"Словацькі крони","rate":0.11992,"cc":"SKK","exchangedate":"19.07.2002"
 }
,{ 
"r030":752,"txt":"Шведська крона","rate":0.577679,"cc":"SEK","exchangedate":"19.07.2002"
 }
,{ 
"r030":756,"txt":"Швейцарський франк","rate":3.660502,"cc":"CHF","exchangedate":"19.07.2002"
 }
,{ 
"r030":792,"txt":"Турецькі ліри","rate":0.0000032,"cc":"TRL","exchangedate":"19.07.2002"
 }
,{ 
"r030":795,"txt":"Манати Туркменії","rate":0.00102477,"cc":"TMM","exchangedate":"19.07.2002"
 }
,{ 
"r030":826,"txt":"Фунт стерлінгів","rate":8.338063,"cc":"GBP","exchangedate":"19.07.2002"
 }
,{ 
"r030":840,"txt":"Долар США","rate":5.3288,"cc":"USD","exchangedate":"19.07.2002"
 }
,{ 
"r030":860,"txt":"Узбецький сум","rate":0.007039,"cc":"UZS","exchangedate":"19.07.2002"
 }
,{ 
"r030":960,"txt":"СПЗ(спец.права запозичення)","rate":7.1349,"cc":"XDR","exchangedate":"19.07.2002"
 }
,{ 
"r030":974,"txt":"Бiлоруський рубль","rate":0.00293,"cc":"BYR","exchangedate":"19.07.2002"
 }
,{ 
"r030":978,"txt":"Євро","rate":5.359707,"cc":"EUR","exchangedate":"19.07.2002"
 }
,{ 
"r030":985,"txt":"Злотий","rate":1.314201,"cc":"PLN","exchangedate":"19.07.2002"
 }
,{ 
"r030":810,"txt":"Російські рублі","rate":0.16896,"cc":"RUR","exchangedate":"19.07.2002"
 }
,{ 
"r030":959,"txt":"Золото","rate":1687.098,"cc":"XAU","exchangedate":"19.07.2002"
 }
,{ 
"r030":961,"txt":"Срiбло","rate":26.617,"cc":"XAG","exchangedate":"19.07.2002"
 }
,{ 
"r030":962,"txt":"Платина","rate":2797.62,"cc":"XPT","exchangedate":"19.07.2002"
 }
,{ 
"r030":964,"txt":"Паладiй","rate":1721.202,"cc":"XPD","exchangedate":"19.07.2002"
 }
]
