[
{ 
"r030":31,"txt":"Азербайджанський манат","rate":0.00108487,"cc":"AZM","exchangedate":"24.06.2004"
 }
,{ 
"r030":36,"txt":"Австралійський долар","rate":3.652595,"cc":"AUD","exchangedate":"24.06.2004"
 }
,{ 
"r030":124,"txt":"Канадський долар","rate":3.916132,"cc":"CAD","exchangedate":"24.06.2004"
 }
,{ 
"r030":203,"txt":"Чеська крона","rate":0.201689,"cc":"CZK","exchangedate":"24.06.2004"
 }
,{ 
"r030":208,"txt":"Данська крона","rate":0.865276,"cc":"DKK","exchangedate":"24.06.2004"
 }
,{ 
"r030":233,"txt":"Крони Естонії","rate":0.41107,"cc":"EEK","exchangedate":"24.06.2004"
 }
,{ 
"r030":348,"txt":"Форинт","rate":0.0253023,"cc":"HUF","exchangedate":"24.06.2004"
 }
,{ 
"r030":352,"txt":"Ісландські крони","rate":0.073256,"cc":"ISK","exchangedate":"24.06.2004"
 }
,{ 
"r030":392,"txt":"Єна","rate":0.0488743,"cc":"JPY","exchangedate":"24.06.2004"
 }
,{ 
"r030":398,"txt":"Теньге","rate":0.038998,"cc":"KZT","exchangedate":"24.06.2004"
 }
,{ 
"r030":428,"txt":"Лати Латвії","rate":9.763853,"cc":"LVL","exchangedate":"24.06.2004"
 }
,{ 
"r030":440,"txt":"Литовські лити","rate":1.861245,"cc":"LTL","exchangedate":"24.06.2004"
 }
,{ 
"r030":498,"txt":"Молдовський лей","rate":0.44542,"cc":"MDL","exchangedate":"24.06.2004"
 }
,{ 
"r030":578,"txt":"Норвезька крона","rate":0.769913,"cc":"NOK","exchangedate":"24.06.2004"
 }
,{ 
"r030":643,"txt":"Російський рубль","rate":0.18334,"cc":"RUB","exchangedate":"24.06.2004"
 }
,{ 
"r030":702,"txt":"Сінгапурський долар","rate":3.096406,"cc":"SGD","exchangedate":"24.06.2004"
 }
,{ 
"r030":703,"txt":"Словацькі крони","rate":0.161038,"cc":"SKK","exchangedate":"24.06.2004"
 }
,{ 
"r030":752,"txt":"Шведська крона","rate":0.701899,"cc":"SEK","exchangedate":"24.06.2004"
 }
,{ 
"r030":756,"txt":"Швейцарський франк","rate":4.240691,"cc":"CHF","exchangedate":"24.06.2004"
 }
,{ 
"r030":792,"txt":"Турецькі ліри","rate":0.00000357,"cc":"TRL","exchangedate":"24.06.2004"
 }
,{ 
"r030":795,"txt":"Манати Туркменії","rate":0.00102333,"cc":"TMM","exchangedate":"24.06.2004"
 }
,{ 
"r030":826,"txt":"Фунт стерлінгів","rate":9.670509,"cc":"GBP","exchangedate":"24.06.2004"
 }
,{ 
"r030":840,"txt":"Долар США","rate":5.3213,"cc":"USD","exchangedate":"24.06.2004"
 }
,{ 
"r030":860,"txt":"Узбецький сум","rate":0.005224,"cc":"UZS","exchangedate":"24.06.2004"
 }
,{ 
"r030":960,"txt":"СПЗ(спец.права запозичення)","rate":7.786007,"cc":"XDR","exchangedate":"24.06.2004"
 }
,{ 
"r030":974,"txt":"Бiлоруський рубль","rate":0.00247,"cc":"BYR","exchangedate":"24.06.2004"
 }
,{ 
"r030":978,"txt":"Євро","rate":6.431855,"cc":"EUR","exchangedate":"24.06.2004"
 }
,{ 
"r030":985,"txt":"Злотий","rate":1.405594,"cc":"PLN","exchangedate":"24.06.2004"
 }
,{ 
"r030":51,"txt":"Вiрменський драм","rate":0.00971007,"cc":"AMD","exchangedate":"24.06.2004"
 }
,{ 
"r030":100,"txt":"Болгарські леви","rate":0.3288255,"cc":"BGL","exchangedate":"24.06.2004"
 }
,{ 
"r030":152,"txt":"Чілійські песо","rate":0.0082912,"cc":"CLP","exchangedate":"24.06.2004"
 }
,{ 
"r030":156,"txt":"Юань Женьмiньбi","rate":0.643333,"cc":"CNY","exchangedate":"24.06.2004"
 }
,{ 
"r030":191,"txt":"Куна","rate":0.865291,"cc":"HRK","exchangedate":"24.06.2004"
 }
,{ 
"r030":255,"txt":"Долари США по розр. з Індією","rate":4.26,"cc":"___","exchangedate":"24.06.2004"
 }
,{ 
"r030":344,"txt":"Гонконгівський долар","rate":0.683261,"cc":"HKD","exchangedate":"24.06.2004"
 }
,{ 
"r030":356,"txt":"Індійська рупія","rate":0.1177316,"cc":"INR","exchangedate":"24.06.2004"
 }
,{ 
"r030":364,"txt":"Іранський ріал","rate":0.0006211,"cc":"IRR","exchangedate":"24.06.2004"
 }
,{ 
"r030":368,"txt":"Іракський динар","rate":0.00363,"cc":"IQD","exchangedate":"24.06.2004"
 }
,{ 
"r030":376,"txt":"Новий ізраїльський шекель","rate":1.162664,"cc":"ILS","exchangedate":"24.06.2004"
 }
,{ 
"r030":410,"txt":"Вона","rate":0.0045519,"cc":"KRW","exchangedate":"24.06.2004"
 }
,{ 
"r030":414,"txt":"Кувейтські динари","rate":18.063094,"cc":"KWD","exchangedate":"24.06.2004"
 }
,{ 
"r030":417,"txt":"Сом","rate":0.121449,"cc":"KGS","exchangedate":"24.06.2004"
 }
,{ 
"r030":422,"txt":"Ліванський фунт","rate":0.003516,"cc":"LBP","exchangedate":"24.06.2004"
 }
,{ 
"r030":434,"txt":"Лівійський динар","rate":3.995048,"cc":"LYD","exchangedate":"24.06.2004"
 }
,{ 
"r030":470,"txt":"Мальтійські ліри","rate":15.216966,"cc":"MTL","exchangedate":"24.06.2004"
 }
,{ 
"r030":484,"txt":"Мексіканський песо","rate":0.460123,"cc":"MXN","exchangedate":"24.06.2004"
 }
,{ 
"r030":496,"txt":"Монгольский тугрик","rate":0.00458656,"cc":"MNT","exchangedate":"24.06.2004"
 }
,{ 
"r030":554,"txt":"Новозеландський долар","rate":3.350156,"cc":"NZD","exchangedate":"24.06.2004"
 }
,{ 
"r030":586,"txt":"Пакистанська рупія","rate":0.092192,"cc":"PKR","exchangedate":"24.06.2004"
 }
,{ 
"r030":604,"txt":"Перуанский соль","rate":1.527101,"cc":"PEN","exchangedate":"24.06.2004"
 }
,{ 
"r030":642,"txt":"новий румунські леї","rate":0.00015904,"cc":"ROL","exchangedate":"24.06.2004"
 }
,{ 
"r030":682,"txt":"Саудівський рiял","rate":1.419924,"cc":"SAR","exchangedate":"24.06.2004"
 }
,{ 
"r030":704,"txt":"Донг","rate":0.00033768,"cc":"VND","exchangedate":"24.06.2004"
 }
,{ 
"r030":705,"txt":"Словенські толари","rate":0.027121,"cc":"SIT","exchangedate":"24.06.2004"
 }
,{ 
"r030":760,"txt":"Сирійский фунт","rate":0.106896,"cc":"SYP","exchangedate":"24.06.2004"
 }
,{ 
"r030":818,"txt":"Єгипетський фунт","rate":0.857488,"cc":"EGP","exchangedate":"24.06.2004"
 }
,{ 
"r030":901,"txt":"Новий тайванський долар","rate":0.15924,"cc":"TWD","exchangedate":"24.06.2004"
 }
,{ 
"r030":952,"txt":"Франки CFA-BCEAO","rate":0.0097561,"cc":"XOF","exchangedate":"24.06.2004"
 }
,{ 
"r030":972,"txt":"Сомонi","rate":1.821073,"cc":"TJS","exchangedate":"24.06.2004"
 }
,{ 
"r030":981,"txt":"Ларi","rate":2.773438,"cc":"GEL","exchangedate":"24.06.2004"
 }
,{ 
"r030":986,"txt":"Бразильський реал","rate":1.670326,"cc":"BRL","exchangedate":"24.06.2004"
 }
,{ 
"r030":959,"txt":"Золото","rate":2103.244,"cc":"XAU","exchangedate":"24.06.2004"
 }
,{ 
"r030":961,"txt":"Срiбло","rate":31.289,"cc":"XAG","exchangedate":"24.06.2004"
 }
,{ 
"r030":962,"txt":"Платина","rate":4304.932,"cc":"XPT","exchangedate":"24.06.2004"
 }
,{ 
"r030":964,"txt":"Паладiй","rate":1197.293,"cc":"XPD","exchangedate":"24.06.2004"
 }
]
