[
{ 
"r030":31,"txt":"Азербайджанський манат","rate":0.09970069,"cc":"AZM","exchangedate":"28.12.2010"
 }
,{ 
"r030":36,"txt":"Австралійський долар","rate":7.975064,"cc":"AUD","exchangedate":"28.12.2010"
 }
,{ 
"r030":124,"txt":"Канадський долар","rate":7.898566,"cc":"CAD","exchangedate":"28.12.2010"
 }
,{ 
"r030":156,"txt":"Юань Женьмiньбi","rate":1.200627,"cc":"CNY","exchangedate":"28.12.2010"
 }
,{ 
"r030":203,"txt":"Чеська крона","rate":0.412533,"cc":"CZK","exchangedate":"28.12.2010"
 }
,{ 
"r030":208,"txt":"Данська крона","rate":1.403116,"cc":"DKK","exchangedate":"28.12.2010"
 }
,{ 
"r030":233,"txt":"Крони Естонії","rate":0.668369,"cc":"EEK","exchangedate":"28.12.2010"
 }
,{ 
"r030":348,"txt":"Форинт","rate":0.0375057,"cc":"HUF","exchangedate":"28.12.2010"
 }
,{ 
"r030":352,"txt":"Ісландські крони","rate":0.036061,"cc":"ISK","exchangedate":"28.12.2010"
 }
,{ 
"r030":392,"txt":"Єна","rate":0.0960391,"cc":"JPY","exchangedate":"28.12.2010"
 }
,{ 
"r030":398,"txt":"Теньге","rate":0.05401,"cc":"KZT","exchangedate":"28.12.2010"
 }
,{ 
"r030":428,"txt":"Лати Латвії","rate":14.745771,"cc":"LVL","exchangedate":"28.12.2010"
 }
,{ 
"r030":440,"txt":"Литовські лити","rate":3.02876,"cc":"LTL","exchangedate":"28.12.2010"
 }
,{ 
"r030":498,"txt":"Молдовський лей","rate":0.656569,"cc":"MDL","exchangedate":"28.12.2010"
 }
,{ 
"r030":578,"txt":"Норвезька крона","rate":1.334742,"cc":"NOK","exchangedate":"28.12.2010"
 }
,{ 
"r030":643,"txt":"Російський рубль","rate":0.26145,"cc":"RUB","exchangedate":"28.12.2010"
 }
,{ 
"r030":702,"txt":"Сінгапурський долар","rate":6.117403,"cc":"SGD","exchangedate":"28.12.2010"
 }
,{ 
"r030":752,"txt":"Шведська крона","rate":1.164931,"cc":"SEK","exchangedate":"28.12.2010"
 }
,{ 
"r030":756,"txt":"Швейцарський франк","rate":8.282671,"cc":"CHF","exchangedate":"28.12.2010"
 }
,{ 
"r030":792,"txt":"Турецькі ліри","rate":0.05137405,"cc":"TRL","exchangedate":"28.12.2010"
 }
,{ 
"r030":795,"txt":"Манати Туркменії","rate":0.02793368,"cc":"TMM","exchangedate":"28.12.2010"
 }
,{ 
"r030":826,"txt":"Фунт стерлінгів","rate":12.269976,"cc":"GBP","exchangedate":"28.12.2010"
 }
,{ 
"r030":840,"txt":"Долар США","rate":7.9611,"cc":"USD","exchangedate":"28.12.2010"
 }
,{ 
"r030":860,"txt":"Узбецький сум","rate":0.004854,"cc":"UZS","exchangedate":"28.12.2010"
 }
,{ 
"r030":960,"txt":"СПЗ(спец.права запозичення)","rate":12.175859,"cc":"XDR","exchangedate":"28.12.2010"
 }
,{ 
"r030":974,"txt":"Бiлоруський рубль","rate":0.00265,"cc":"BYR","exchangedate":"28.12.2010"
 }
,{ 
"r030":978,"txt":"Євро","rate":10.457701,"cc":"EUR","exchangedate":"28.12.2010"
 }
,{ 
"r030":985,"txt":"Злотий","rate":2.630008,"cc":"PLN","exchangedate":"28.12.2010"
 }
,{ 
"r030":51,"txt":"Вiрменський драм","rate":0.02209419,"cc":"AMD","exchangedate":"28.12.2010"
 }
,{ 
"r030":100,"txt":"Болгарські леви","rate":0.5335563,"cc":"BGL","exchangedate":"28.12.2010"
 }
,{ 
"r030":152,"txt":"Чілійські песо","rate":0.0164467,"cc":"CLP","exchangedate":"28.12.2010"
 }
,{ 
"r030":191,"txt":"Куна","rate":1.404954,"cc":"HRK","exchangedate":"28.12.2010"
 }
,{ 
"r030":255,"txt":"Долари США по розр. з Індією","rate":6.3504,"cc":"___","exchangedate":"28.12.2010"
 }
,{ 
"r030":344,"txt":"Гонконгівський долар","rate":1.022507,"cc":"HKD","exchangedate":"28.12.2010"
 }
,{ 
"r030":356,"txt":"Індійська рупія","rate":0.1731487,"cc":"INR","exchangedate":"28.12.2010"
 }
,{ 
"r030":364,"txt":"Іранський ріал","rate":0.0007629,"cc":"IRR","exchangedate":"28.12.2010"
 }
,{ 
"r030":368,"txt":"Іракський динар","rate":0.006805,"cc":"IQD","exchangedate":"28.12.2010"
 }
,{ 
"r030":376,"txt":"Новий ізраїльський шекель","rate":2.161765,"cc":"ILS","exchangedate":"28.12.2010"
 }
,{ 
"r030":410,"txt":"Вона","rate":0.0068508,"cc":"KRW","exchangedate":"28.12.2010"
 }
,{ 
"r030":414,"txt":"Кувейтські динари","rate":28.138958,"cc":"KWD","exchangedate":"28.12.2010"
 }
,{ 
"r030":417,"txt":"Сом","rate":0.169437,"cc":"KGS","exchangedate":"28.12.2010"
 }
,{ 
"r030":422,"txt":"Ліванський фунт","rate":0.0052902,"cc":"LBP","exchangedate":"28.12.2010"
 }
,{ 
"r030":434,"txt":"Лівійський динар","rate":6.341269,"cc":"LYD","exchangedate":"28.12.2010"
 }
,{ 
"r030":484,"txt":"Мексіканський песо","rate":0.634735,"cc":"MXN","exchangedate":"28.12.2010"
 }
,{ 
"r030":496,"txt":"Монгольский тугрик","rate":0.00634786,"cc":"MNT","exchangedate":"28.12.2010"
 }
,{ 
"r030":554,"txt":"Новозеландський долар","rate":5.9157,"cc":"NZD","exchangedate":"28.12.2010"
 }
,{ 
"r030":586,"txt":"Пакистанська рупія","rate":0.092534,"cc":"PKR","exchangedate":"28.12.2010"
 }
,{ 
"r030":604,"txt":"Перуанский соль","rate":2.818392,"cc":"PEN","exchangedate":"28.12.2010"
 }
,{ 
"r030":642,"txt":"новий румунські леї","rate":0.02430034,"cc":"ROL","exchangedate":"28.12.2010"
 }
,{ 
"r030":682,"txt":"Саудівський рiял","rate":2.116913,"cc":"SAR","exchangedate":"28.12.2010"
 }
,{ 
"r030":704,"txt":"Донг","rate":0.00040713,"cc":"VND","exchangedate":"28.12.2010"
 }
,{ 
"r030":760,"txt":"Сирійский фунт","rate":0.170893,"cc":"SYP","exchangedate":"28.12.2010"
 }
,{ 
"r030":818,"txt":"Єгипетський фунт","rate":1.374498,"cc":"EGP","exchangedate":"28.12.2010"
 }
,{ 
"r030":901,"txt":"Новий тайванський долар","rate":0.260596,"cc":"TWD","exchangedate":"28.12.2010"
 }
,{ 
"r030":952,"txt":"Франки CFA-BCEAO","rate":0.0159926,"cc":"XOF","exchangedate":"28.12.2010"
 }
,{ 
"r030":972,"txt":"Сомонi","rate":1.804214,"cc":"TJS","exchangedate":"28.12.2010"
 }
,{ 
"r030":981,"txt":"Ларi","rate":4.506898,"cc":"GEL","exchangedate":"28.12.2010"
 }
,{ 
"r030":986,"txt":"Бразильський реал","rate":4.601206,"cc":"BRL","exchangedate":"28.12.2010"
 }
,{ 
"r030":959,"txt":"Золото","rate":10990.299,"cc":"XAU","exchangedate":"28.12.2010"
 }
,{ 
"r030":961,"txt":"Срiбло","rate":231.429,"cc":"XAG","exchangedate":"28.12.2010"
 }
,{ 
"r030":962,"txt":"Платина","rate":13732.898,"cc":"XPT","exchangedate":"28.12.2010"
 }
,{ 
"r030":964,"txt":"Паладiй","rate":6082.28,"cc":"XPD","exchangedate":"28.12.2010"
 }
]
